MANIFEST.in
README.rst
setup.py
grvlms_social_media/__about__.py
grvlms_social_media/__init__.py
grvlms_social_media/plugin.py
grvlms_social_media.egg-info/PKG-INFO
grvlms_social_media.egg-info/SOURCES.txt
grvlms_social_media.egg-info/dependency_links.txt
grvlms_social_media.egg-info/entry_points.txt
grvlms_social_media.egg-info/requires.txt
grvlms_social_media.egg-info/top_level.txt
grvlms_social_media/patches/.gitignore
grvlms_social_media/patches/lms-env
grvlms_social_media/patches/openedx-lms-common-settings
grvlms_social_media/templates/social-media/apps/.gitignore
grvlms_social_media/templates/social-media/build/.gitignore
grvlms_social_media/templates/social-media/hooks/.gitignore