Metadata-Version: 1.2
Name: grvlms-social-media
Version: 0.1.1
Summary: socialmedia plugin for Grvlms
Home-page: https://github.com/groovetch/grvlms-social-media
Author: GrooveTechnology
License: AGPLv3
Project-URL: Code, https://github.com/groovetch/grvlms-social-media
Project-URL: Issue tracker, https://github.com/groovetch/grvlms-social-media/issues
Platform: UNKNOWN
Classifier: Development Status :: 3 - Alpha
Classifier: Intended Audience :: Developers
Classifier: License :: OSI Approved :: GNU Affero General Public License v3
Classifier: Operating System :: OS Independent
Classifier: Programming Language :: Python
Classifier: Programming Language :: Python :: 3.5
Classifier: Programming Language :: Python :: 3.6
Classifier: Programming Language :: Python :: 3.7
Requires-Python: >=3.5
